{
  "@context": "https://schema.org",
  "@type": "Article",
  "headline": "Breccia Laser Cleaning",
  "alternativeHeadline": "Advanced Laser Ablation Techniques for Breccia",
  "description": "Breccia laser cleaning utilizes precise pulsed laser ablation to remove surface contaminants from the composite stone matrix. The process exploits the differential absorption between the contamination...",
  "keywords": [
    "stone laser cleaning",
    "art and restoration laser cleaning",
    "breccia",
    "thermal processing",
    "surface restoration",
    "laser ablation",
    "construction laser cleaning",
    "breccia laser cleaning",
    "non-contact cleaning",
    "pulsed fiber laser",
    "surface contamination removal",
    "industrial laser parameters",
    "industrial laser",
    "surface treatment",
    "laser cleaning"
  ],
  "articleSection": "Materials Processing",
  "inLanguage": "en-US",
  "isAccessibleForFree": true,
  "author": {
    "@type": "Person",
    "name": "Yi-Chun Lin"
  },
  "about": {
    "@type": "Material",
    "name": "Breccia",
    "category": "stone",
    "density": "2.5-2.8 g/cm³ (varies with composition)",
    "description": "Breccia material for laser cleaning applications"
  },
  "mainEntity": {
    "@type": "HowTo",
    "name": "How to Laser Clean Breccia",
    "description": "Process for laser cleaning Breccia using 1064 nm (primary), 532 nm (optional for specific contaminant targeting) wavelength",
    "step": [
      {
        "@type": "HowToStep",
        "name": "Material Preparation",
        "text": "Secure Breccia component in laser processing fixture"
      },
      {
        "@type": "HowToStep",
        "name": "Parameter Configuration",
        "text": "Configure laser parameters: 1064 nm (primary), 532 nm (optional for specific contaminant targeting) wavelength"
      },
      {
        "@type": "HowToStep",
        "name": "Surface Treatment",
        "text": "Execute systematic scanning pattern for Breccia processing"
      }
    ]
  },
  "datePublished": "2025-09-20",
  "dateModified": "2025-09-20",
  "publisher": {
    "@type": "Organization",
    "name": "Z-Beam"
  }
}