{
  "material": "Steel",
  "component_type": "table",
  "versions": [
    {
      "material": "Steel",
      "component_type": "table",
      "filepath": "content/components/table/steel-laser-cleaning.md",
      "timestamp": "2025-09-09T17:57:53.628209",
      "generator_version": "2.1.0",
      "system_info": {
        "platform": "Darwin",
        "python_version": "3.12.4",
        "hostname": "Todds-MacBook-Pro.local"
      },
      "author": "AI Assistant"
    },
    {
      "material": "Steel",
      "component_type": "table",
      "filepath": "content/components/table/steel-laser-cleaning.md",
      "timestamp": "2025-09-09T17:57:54.038745",
      "generator_version": "2.1.0",
      "system_info": {
        "platform": "Darwin",
        "python_version": "3.12.4",
        "hostname": "Todds-MacBook-Pro.local"
      },
      "author": "AI Assistant"
    },
    {
      "material": "Steel",
      "component_type": "table",
      "filepath": "content/components/table/steel-laser-cleaning.md",
      "timestamp": "2025-09-09T17:57:54.815475",
      "generator_version": "2.1.0",
      "system_info": {
        "platform": "Darwin",
        "python_version": "3.12.4",
        "hostname": "Todds-MacBook-Pro.local"
      },
      "author": "AI Assistant"
    },
    {
      "material": "Steel",
      "component_type": "table",
      "filepath": "content/components/table/steel-laser-cleaning.md",
      "timestamp": "2025-09-09T17:57:55.224938",
      "generator_version": "2.1.0",
      "system_info": {
        "platform": "Darwin",
        "python_version": "3.12.4",
        "hostname": "Todds-MacBook-Pro.local"
      },
      "author": "AI Assistant"
    },
    {
      "material": "Steel",
      "component_type": "table",
      "filepath": "content/components/table/steel-laser-cleaning.md",
      "timestamp": "2025-09-09T17:58:05.004885",
      "generator_version": "2.1.0",
      "system_info": {
        "platform": "Darwin",
        "python_version": "3.12.4",
        "hostname": "Todds-MacBook-Pro.local"
      },
      "author": "AI Assistant"
    },
    {
      "material": "Steel",
      "component_type": "table",
      "filepath": "content/components/table/steel-laser-cleaning.md",
      "timestamp": "2025-09-09T17:58:08.548562",
      "generator_version": "2.1.0",
      "system_info": {
        "platform": "Darwin",
        "python_version": "3.12.4",
        "hostname": "Todds-MacBook-Pro.local"
      },
      "author": "AI Assistant"
    },
    {
      "material": "Steel",
      "component_type": "table",
      "filepath": "content/components/table/steel-laser-cleaning.md",
      "timestamp": "2025-09-09T17:58:10.018492",
      "generator_version": "2.1.0",
      "system_info": {
        "platform": "Darwin",
        "python_version": "3.12.4",
        "hostname": "Todds-MacBook-Pro.local"
      },
      "author": "AI Assistant"
    },
    {
      "material": "Steel",
      "component_type": "table",
      "filepath": "content/components/table/steel-laser-cleaning.md",
      "timestamp": "2025-09-09T17:58:10.588372",
      "generator_version": "2.1.0",
      "system_info": {
        "platform": "Darwin",
        "python_version": "3.12.4",
        "hostname": "Todds-MacBook-Pro.local"
      },
      "author": "AI Assistant"
    },
    {
      "material": "Steel",
      "component_type": "table",
      "filepath": "content/components/table/steel-laser-cleaning.md",
      "timestamp": "2025-09-09T17:58:12.463159",
      "generator_version": "2.1.0",
      "system_info": {
        "platform": "Darwin",
        "python_version": "3.12.4",
        "hostname": "Todds-MacBook-Pro.local"
      },
      "author": "AI Assistant"
    },
    {
      "material": "Steel",
      "component_type": "table",
      "filepath": "content/components/table/steel-laser-cleaning.md",
      "timestamp": "2025-09-09T17:58:19.748531",
      "generator_version": "2.1.0",
      "system_info": {
        "platform": "Darwin",
        "python_version": "3.12.4",
        "hostname": "Todds-MacBook-Pro.local"
      },
      "author": "AI Assistant"
    }
  ]
}