{
  "material": "Titanium",
  "component_type": "text",
  "versions": [
    {
      "material": "Titanium",
      "component_type": "text",
      "filepath": "content/components/text/titanium-laser-cleaning.md",
      "timestamp": "2025-09-10T15:29:12.028009",
      "generator_version": "2.1.0",
      "system_info": {
        "platform": "Darwin",
        "python_version": "3.12.4",
        "hostname": "Todds-MacBook-Pro.local"
      },
      "author": "AI Assistant"
    },
    {
      "material": "Titanium",
      "component_type": "text",
      "filepath": "content/components/text/titanium-laser-cleaning.md",
      "timestamp": "2025-09-10T15:55:20.454987",
      "generator_version": "2.1.0",
      "system_info": {
        "platform": "Darwin",
        "python_version": "3.12.4",
        "hostname": "Todds-MacBook-Pro.local"
      },
      "author": "AI Assistant"
    },
    {
      "material": "Titanium",
      "component_type": "text",
      "filepath": "content/components/text/titanium-laser-cleaning.md",
      "timestamp": "2025-09-10T15:55:21.323894",
      "generator_version": "2.1.0",
      "system_info": {
        "platform": "Darwin",
        "python_version": "3.12.4",
        "hostname": "Todds-MacBook-Pro.local"
      },
      "author": "AI Assistant"
    },
    {
      "material": "Titanium",
      "component_type": "text",
      "filepath": "content/components/text/titanium-laser-cleaning.md",
      "timestamp": "2025-09-10T15:55:21.893234",
      "generator_version": "2.1.0",
      "system_info": {
        "platform": "Darwin",
        "python_version": "3.12.4",
        "hostname": "Todds-MacBook-Pro.local"
      },
      "author": "AI Assistant"
    },
    {
      "material": "Titanium",
      "component_type": "text",
      "filepath": "content/components/text/titanium-laser-cleaning.md",
      "timestamp": "2025-09-10T15:55:23.926300",
      "generator_version": "2.1.0",
      "system_info": {
        "platform": "Darwin",
        "python_version": "3.12.4",
        "hostname": "Todds-MacBook-Pro.local"
      },
      "author": "AI Assistant"
    },
    {
      "material": "Titanium",
      "component_type": "text",
      "filepath": "content/components/text/titanium-laser-cleaning.md",
      "timestamp": "2025-09-10T15:56:37.945752",
      "generator_version": "2.1.0",
      "system_info": {
        "platform": "Darwin",
        "python_version": "3.12.4",
        "hostname": "Todds-MacBook-Pro.local"
      },
      "author": "AI Assistant"
    },
    {
      "material": "Titanium",
      "component_type": "text",
      "filepath": "content/components/text/titanium-laser-cleaning.md",
      "timestamp": "2025-09-10T15:56:38.894222",
      "generator_version": "2.1.0",
      "system_info": {
        "platform": "Darwin",
        "python_version": "3.12.4",
        "hostname": "Todds-MacBook-Pro.local"
      },
      "author": "AI Assistant"
    },
    {
      "material": "Titanium",
      "component_type": "text",
      "filepath": "content/components/text/titanium-laser-cleaning.md",
      "timestamp": "2025-09-10T15:56:39.647392",
      "generator_version": "2.1.0",
      "system_info": {
        "platform": "Darwin",
        "python_version": "3.12.4",
        "hostname": "Todds-MacBook-Pro.local"
      },
      "author": "AI Assistant"
    },
    {
      "material": "Titanium",
      "component_type": "text",
      "filepath": "content/components/text/titanium-laser-cleaning.md",
      "timestamp": "2025-09-10T15:56:41.661289",
      "generator_version": "2.1.0",
      "system_info": {
        "platform": "Darwin",
        "python_version": "3.12.4",
        "hostname": "Todds-MacBook-Pro.local"
      },
      "author": "AI Assistant"
    },
    {
      "material": "Titanium",
      "component_type": "text",
      "filepath": "content/components/text/titanium-laser-cleaning.md",
      "timestamp": "2025-09-10T15:57:06.861073",
      "generator_version": "2.1.0",
      "system_info": {
        "platform": "Darwin",
        "python_version": "3.12.4",
        "hostname": "Todds-MacBook-Pro.local"
      },
      "author": "AI Assistant"
    }
  ]
}